<!DOCTYPE frameset SYSTEM "framesetTR.dtd">
<frameset>

<predicate lemma="çözümle">


<roleset id="çözümle.01" name="Analiz etmek">
<roles>
<role descr="çözümleyen" f="" n="0" suffix="NOM">
<vnrole vncls="" vntheta="agent"/>
</role>

<role descr="çözümlenen" f="" n="1" suffix="ACC">
<vnrole vncls="" vntheta="topic"/>
</role>

<note/>
</roles>

<example name="" src="" type="">
<inflection aspect="ns" form="ns" person="ns" tense="ns" voice="ns"/>
<text>Kültürel kargaşayı oldukça başarılı bir şekilde çözümledi.</text>


<note/>
<arg f="" n="1" suffix="">Kültürel kargaşayı</arg>
<arg f="mnr" n="m" suffix="">oldukça başarılı bir şekilde</arg>
<rel f="">çözümledi</rel>
</example>

<note/>
</roleset>

<note/>
</predicate>

<note/>
</frameset>
